Metadata-Version: 2.1
Name: damefunniest
Version: 0.4.1
Summary: The funniest joke in the world
Home-page: http://github.com/davidam/damefunniest
Author: David Arroyo Menéndez
Author-email: davidam@gnu.org
License: GPLv3
Keywords: funniest joke comedy flying circus
Platform: UNKNOWN
Classifier: Development Status :: 3 - Alpha
Classifier: License :: OSI Approved :: GNU General Public License v3 (GPLv3)
Classifier: Programming Language :: Python :: 3.6
Classifier: Topic :: Text Processing :: Linguistic
